JrkG2modulePi/JrkG2.py
JrkG2modulePi/__init__.py
JrkG2modulePi-1.1.0.dist-info/METADATA
JrkG2modulePi-1.1.0.dist-info/WHEEL
JrkG2modulePi-1.1.0.dist-info/top_level.txt
JrkG2modulePi-1.1.0.dist-info/RECORD
