Metadata-Version: 2.1
Name: JrkG2modulePi
Version: 1.1.0
Summary: The Jrk G2 library for Linux, RaspberryPi.
Home-page: https://github.com/sgrsn/JrkG2modulePi
Author: UNKNOWN
Author-email: UNKNOWN
License: MIT License
Keywords: Jrk,JrkG2,Pololu,Suzakulab
Platform: UNKNOWN
Classifier: License :: OSI Approved :: MIT License
Classifier: Programming Language :: Python :: 2.7
Requires-Dist: pyserial
Requires-Dist: smbus2
Requires-Dist: enum34
